topsis/102217044.py
topsis/__init__.py
Topsis_Devit_102217044-1.0.1.dist-info/LICENSE
Topsis_Devit_102217044-1.0.1.dist-info/METADATA
Topsis_Devit_102217044-1.0.1.dist-info/WHEEL
Topsis_Devit_102217044-1.0.1.dist-info/top_level.txt
Topsis_Devit_102217044-1.0.1.dist-info/RECORD
