Metadata-Version: 2.1
Name: Topsis-Devit-102217044
Version: 1.0.1
Home-page: https://github.com/devitsah/Topsis-Devit-102217044
Author: Devit Sah
Author-email: dsah_be22@thapar.edu
Classifier: Programming Language :: Python :: 3
Classifier: License :: OSI Approved :: MIT License
Classifier: Operating System :: OS Independent
Requires-Python: >=3.6
License-File: LICENSE
Requires-Dist: pandas
Requires-Dist: numpy
